RPA/Sema4AI.py
RPA/_support.py
rpaframework_sema4ai-1.0.0.dist-info/METADATA
rpaframework_sema4ai-1.0.0.dist-info/WHEEL
rpaframework_sema4ai-1.0.0.dist-info/licenses/LICENSE
rpaframework_sema4ai-1.0.0.dist-info/RECORD
