Metadata-Version: 2.4
Name: rpaframework-sema4ai
Version: 1.0.0
Summary: Sema4ai library for RPA Framework
Author-email: RPA Framework <rpafw@robocorp.com>
License: Apache-2.0
License-File: LICENSE
Keywords: automation,robotframework,rpa,sema4ai
Classifier: Development Status :: 3 - Alpha
Classifier: Framework :: Robot Framework
Classifier: Framework :: Robot Framework :: Library
Classifier: Intended Audience :: Developers
Classifier: License :: OSI Approved :: Apache Software License
Classifier: Operating System :: OS Independent
Classifier: Programming Language :: Python :: 3.10
Classifier: Programming Language :: Python :: 3.11
Classifier: Programming Language :: Python :: 3.12
Classifier: Topic :: Software Development :: Libraries
Classifier: Topic :: Software Development :: Libraries :: Python Modules
Requires-Python: >=3.10
Requires-Dist: pydantic>=2.11.7
Requires-Dist: robocorp>=3.0.0
Requires-Dist: sema4ai-actions>=1.4.2
Requires-Dist: setuptools>=65.0.0
Requires-Dist: wheel>=0.40.0
